iautolib/__init__.py
iautolib/__main__.py
iautolib/clickFinder.py
iautolib/ilib.py
iautolib/index.py
iautolib/photo_rc.py
iautolib/icons/bot.jpg
iautolib/icons/bot1.png
iautolib/icons/bot2.png
iautolib/icons/browse.png
iautolib/icons/code.png
iautolib/icons/copy.png
iautolib/icons/help.png
iautolib/icons/home.png
iautolib/icons/pic.png
iautolib/icons/settings.png
iautolib/icons/stanbic.png
iautolib/icons/vpn.png
iautolib/themes/classic.css
iautolib/themes/darkblue.css
iautolib/themes/qdark.css
iautolib/themes/waitimage.ui
stanbic_iautolib-1.1.3.dist-info/LICENSE
stanbic_iautolib-1.1.3.dist-info/METADATA
stanbic_iautolib-1.1.3.dist-info/WHEEL
stanbic_iautolib-1.1.3.dist-info/entry_points.txt
stanbic_iautolib-1.1.3.dist-info/top_level.txt
stanbic_iautolib-1.1.3.dist-info/RECORD
